README.rst
setup.py
st/__init__.py
st/chain.py
st/enum.py
st/foreach.py
st/make_cache.py
st/partial.py
st/process.py
st/run.py
st/serialize.py
st/singleton.py
st/time_point.py
st.egg-info/PKG-INFO
st.egg-info/SOURCES.txt
st.egg-info/dependency_links.txt
st.egg-info/requires.txt
st.egg-info/top_level.txt