Metadata-Version: 1.1
Name: st
Version: 0.0.8
Summary: Sf Tools for Python3 Development
Home-page: https://github.com/sf-zhou/st
Author: SF-Zhou
Author-email: sfzhou.scut@gmail.com
License: MIT
Keywords: tools
Platform: UNKNOWN
Classifier: Development Status :: 3 - Alpha
Classifier: Intended Audience :: Developers
Classifier: License :: OSI Approved :: MIT License
Classifier: Programming Language :: Python :: 3
Classifier: Programming Language :: Python :: 3.3
Classifier: Programming Language :: Python :: 3.4
Classifier: Programming Language :: Python :: 3.5
